main.py
mcp_server_weather-0.1.3.dist-info/METADATA
mcp_server_weather-0.1.3.dist-info/WHEEL
mcp_server_weather-0.1.3.dist-info/entry_points.txt
mcp_server_weather-0.1.3.dist-info/top_level.txt
mcp_server_weather-0.1.3.dist-info/RECORD
